{"XYZ":{"s":1769783400,"p":[61.74,61.26,61.01,60.64,60.72,60.72,60.67,61.03,61.06,61.01,null,null,null,null,null,null,null,null,null,null,null,null,null,null,null,null,null,null,null,null,null,null,null,null,null,null,null,null,null,null,null,null,null,null,null,null,null,null,null,null,null,null,null,null,null,null,null,null,null,null,null,null,null,null,null,null,null,null,null,null,null,null,null,null,null,null,null,60.43]},"XOM":{"s":1770042600,"p":[139.43]},"XEL":{"s":1770042600,"p":[75.78]},"XYL":{"s":1770042600,"p":[137.7]}}